tigerseg/__init__.py
tigerseg/segment.py
tigerseg/console/__aseg2__.py
tigerseg/console/__aseg__.py
tigerseg/console/__cine4d__.py
tigerseg/console/__init__.py
tigerseg/console/__main__.py
tigerseg/console/__tigerbet__.py
tigerseg/console/__vdm__.py
tigerseg/methods/__init__.py
tigerseg/methods/cine4d.py
tigerseg/methods/mprage.py
tigerseg/methods/vdm.py
tigerseg-0.1.7.dist-info/LICENCE.txt
tigerseg-0.1.7.dist-info/LICENSE
tigerseg-0.1.7.dist-info/METADATA
tigerseg-0.1.7.dist-info/WHEEL
tigerseg-0.1.7.dist-info/entry_points.txt
tigerseg-0.1.7.dist-info/top_level.txt
tigerseg-0.1.7.dist-info/RECORD
